midiharmony/MIDI.py
midiharmony/README.md
midiharmony/TMIDIX.py
midiharmony/__init__.py
midiharmony/helpers.py
midiharmony/midi_to_colab_audio.py
midiharmony/midiharmony.py
midiharmony/artwork/Project-Los-Angeles.png
midiharmony/artwork/README.md
midiharmony/artwork/Tegridy-Code-2026.png
midiharmony/artwork/__init__.py
midiharmony/artwork/midiharmony.png
midiharmony/data/README.md
midiharmony/data/__init__.py
midiharmony/data/all_harmonic_chords_quads.npz
midiharmony-26.1.32.dist-info/licenses/LICENSE
midiharmony-26.1.32.dist-info/METADATA
midiharmony-26.1.32.dist-info/WHEEL
midiharmony-26.1.32.dist-info/top_level.txt
midiharmony-26.1.32.dist-info/RECORD
