Metadata-Version: 2.4
Name: midiharmony
Version: 26.1.32
Summary: Fast, data‑driven harmony analysis for any MIDI file
Author-email: Alex Lev <alexlev61@proton.me>
Maintainer-email: Alex Lev <alexlev61@proton.me>
License-Expression: Apache-2.0
Project-URL: Homepage, https://github.com/asigalov61/midiharmony
Project-URL: SoundCloud, https://soundcloud.com/aleksandr-sigalov-61/
Project-URL: Documentation, https://github.com/asigalov61/midiharmony
Project-URL: Issues, https://github.com/asigalov61/midiharmony/issues
Project-URL: Discussions, https://github.com/asigalov61/midiharmony/discussions
Project-URL: Dataset, https://huggingface.co/datasets/projectlosangeles/Discover-MIDI-Dataset
Keywords: MIDI,MIDI harmony,harmony,symbolic music,music,music harmony,harmony analysis,harmonic analysis,music information retrieval,MIR,music discovery,music search,music quality,music metadata,music recommendation,research,musicology,music analysis
Classifier: Development Status :: 5 - Production/Stable
Classifier: Intended Audience :: Developers
Classifier: Intended Audience :: Science/Research
Classifier: Intended Audience :: Education
Classifier: Operating System :: OS Independent
Classifier: Programming Language :: Python :: 3
Classifier: Programming Language :: Python :: 3 :: Only
Classifier: Programming Language :: Python :: 3.8
Classifier: Programming Language :: Python :: 3.9
Classifier: Programming Language :: Python :: 3.10
Classifier: Programming Language :: Python :: 3.11
Classifier: Programming Language :: Python :: 3.12
Classifier: Topic :: Multimedia :: Sound/Audio
Classifier: Topic :: Multimedia :: Sound/Audio :: MIDI
Classifier: Topic :: Scientific/Engineering :: Information Analysis
Classifier: Topic :: Software Development :: Libraries :: Python Modules
Classifier: Environment :: Console
Classifier: Natural Language :: English
Classifier: Typing :: Typed
Requires-Python: >=3.8
License-File: LICENSE
Requires-Dist: tqdm
Requires-Dist: matplotlib
Requires-Dist: numpy==1.26.4
Provides-Extra: gpu
Requires-Dist: cupy-cuda12x; extra == "gpu"
Requires-Dist: numpy==1.26.4; extra == "gpu"
Dynamic: license-file
